[
  {
    "任務分類": "專案環境設定",
    "計劃任務": "gradle task fail、環境變數管理、路徑別名",
    "任務數量": 3,
    "完成數量": 3,
    "未完成數量": 0,
    "進度": 100,
    "優先": 3,
    "影響": 1,
    "價值": 1
  },
  {
    "任務分類": "專案插件整合",
    "計劃任務": "Storybook 插件、整合 nativewind 與 figma",
    "任務數量": 2,
    "完成數量": 2,
    "未完成數量": 0,
    "進度": 100,
    "優先": 1,
    "影響": 1,
    "價值": 1
  },
  {
    "任務分類": "文件撰寫與整理",
    "計劃任務": "撰寫相關文件",
    "任務數量": 1,
    "完成數量": 1,
    "未完成數量": 0,
    "進度": 100,
    "優先": 1,
    "影響": 1,
    "價值": 1
  },
  {
    "任務分類": "功能模組拆分",
    "計劃任務": "拆分 APP 共用元件",
    "任務數量": 1,
    "完成數量": 0,
    "未完成數量": 1,
    "進度": 0,
    "優先": 3,
    "影響": 2,
    "價值": 1
  },
  {
    "任務分類": "AI 研究",
    "計劃任務": "研究 AI 釐清需求",
    "任務數量": 1,
    "完成數量": 0,
    "未完成數量": 1,
    "進度": 50,
    "優先": 3,
    "影響": 3,
    "價值": 3
  }
]
